cascadia/__init__.py
cascadia/augment.py
cascadia/cascadia.py
cascadia/model.py
cascadia/utils.py
cascadia/version.py
cascadia/depthcharge/__init__.py
cascadia/depthcharge/constants.py
cascadia/depthcharge/feedforward.py
cascadia/depthcharge/primitives.py
cascadia/depthcharge/utils.py
cascadia/depthcharge/version.py
cascadia/depthcharge/data/__init__.py
cascadia/depthcharge/data/parsers.py
cascadia/depthcharge/data/peptide_datasets.py
cascadia/depthcharge/data/preprocessing.py
cascadia/depthcharge/data/spectrum_datasets.py
cascadia/depthcharge/encoders/__init__.py
cascadia/depthcharge/encoders/sinusoidal.py
cascadia/depthcharge/tokenizers/__init__.py
cascadia/depthcharge/tokenizers/peptides.py
cascadia/depthcharge/tokenizers/tokenizer.py
cascadia/depthcharge/transformers/__init__.py
cascadia/depthcharge/transformers/peptides.py
cascadia/depthcharge/transformers/spectra.py
docs/source/conf.py
cascadia-0.0.5.dist-info/LICENSE
cascadia-0.0.5.dist-info/METADATA
cascadia-0.0.5.dist-info/WHEEL
cascadia-0.0.5.dist-info/entry_points.txt
cascadia-0.0.5.dist-info/top_level.txt
cascadia-0.0.5.dist-info/RECORD
